{"umutears":{"id":"578428710890242056","guildId":"296167427652321302","animated":false,"oldName":"umuTears"},"umu":{"id":"578428711318323210","guildId":"296167427652321302","animated":false,"oldName":"umu"},"umucheer":{"id":"606978963440664615","guildId":"296167427652321302","animated":true,"oldName":"umuCheer"},"umupatanimated":{"id":"606978965663514674","guildId":"296167427652321302","animated":true,"oldName":"umuPatanimated"},"umuumu":{"id":"606987143314931713","guildId":"296167427652321302","animated":true,"oldName":"UmuUmu"},"umuheh":{"id":"626644585635905538","guildId":"296167427652321302","animated":false,"oldName":"umuHeh"},"umuworried":{"id":"626644586080632832","guildId":"296167427652321302","animated":false,"oldName":"umuWorried"},"umuwow":{"id":"626644587800297476","guildId":"296167427652321302","animated":false,"oldName":"umuWow"},"uwaaaa":{"id":"684581259388649598","guildId":"296167427652321302","animated":false,"oldName":"Uwaaaa"},"umu_umu":{"id":"717579306993451008","guildId":"296167427652321302","animated":false,"oldName":"umu_umu"},"umupensive":{"id":"786987131612037181","guildId":"296167427652321302","animated":false,"oldName":"umuPensive"},"umaruchilling":{"id":"847801083777777704","guildId":"296167427652321302","animated":false,"oldName":"umaruChilling"},"uhohbyebyepeener":{"id":"979589101156171807","guildId":"296167427652321302","animated":true,"oldName":"UhohByebyePeener"},"umugasm":{"id":"981963536458743848","guildId":"296167427652321302","animated":false,"oldName":"umuGasm"},"umaruparty":{"id":"422359046079643668","guildId":"321845546534830085","animated":true,"oldName":"UmaruParty"},"ultrachomp":{"id":"488850348686180352","guildId":"321845546534830085","animated":true,"oldName":"UltraChomp"},"upsidedown_cry":{"id":"662482791153270804","guildId":"321845546534830085","animated":false,"oldName":"upsidedown_cry"},"umaruteehee":{"id":"742423362222948372","guildId":"321845546534830085","animated":false,"oldName":"UmaruTeehee"},"uhokay":{"id":"814486714415317002","guildId":"361544468114964480","animated":false,"oldName":"UhOkay"},"umarusigh":{"id":"814547122081890324","guildId":"361544468114964480","animated":true,"oldName":"UmaruSigh"},"uwaaa":{"id":"814562274395029555","guildId":"361544468114964480","animated":true,"oldName":"Uwaaa"},"umarusip":{"id":"860518714796408853","guildId":"361544468114964480","animated":false,"oldName":"umarusip"},"umarusmug":{"id":"860518729706897418","guildId":"361544468114964480","animated":false,"oldName":"umarusmug"},"umaruuhh":{"id":"860518740273528833","guildId":"361544468114964480","animated":false,"oldName":"umaruuhh"},"umaruwtf":{"id":"860519078207422514","guildId":"361544468114964480","animated":false,"oldName":"umaruwtf"},"uwu":{"id":"906300278901440512","guildId":"361544468114964480","animated":false,"oldName":"uwu"},"urmum":{"id":"928425429147197510","guildId":"361544468114964480","animated":true,"oldName":"urmum"},"umaruhehe":{"id":"933294477378977812","guildId":"361544468114964480","animated":false,"oldName":"umaruhehe"},"usagiwow":{"id":"961085284102058075","guildId":"361544468114964480","animated":false,"oldName":"usagiwow"},"uglycry":{"id":"1080933510124150966","guildId":"361544468114964480","animated":false,"oldName":"uglycry"},"ultrawow":{"id":"692923771023130715","guildId":"378599231583289346","animated":true,"oldName":"ultraWOW"},"ughmasami":{"id":"700137731640000592","guildId":"378599231583289346","animated":false,"oldName":"UghMasami"},"uwudance":{"id":"781384732104458250","guildId":"378599231583289346","animated":true,"oldName":"uwudance"},"umarucrybaby":{"id":"610092066080292874","guildId":"422495634172542986","animated":true,"oldName":"UmaruCrybaby"},"unapog":{"id":"755721782303916093","guildId":"422495634172542986","animated":false,"oldName":"UnaPog"},"uwu_0":{"id":"491322400915587072","guildId":"490789406102388737","animated":false,"oldName":"uwu"},"uid":{"id":"773587748527276033","guildId":"522681957373575168","animated":false,"oldName":"UID"},"uyuyeah":{"id":"975083633587159164","guildId":"558322816416743459","animated":false,"oldName":"UyuYeah"},"upvote":{"id":"1048778155705499678","guildId":"564465841517625384","animated":true,"oldName":"Upvote"},"up":{"id":"1125437501067251862","guildId":"641041507985522704","animated":false,"oldName":"up"},"urcute":{"id":"1151443021905268756","guildId":"674108408902713364","animated":false,"oldName":"UrCute"},"umaruhack":{"id":"874447864108032010","guildId":"674357369106464918","animated":true,"oldName":"umaruhack"},"uhmmnope":{"id":"881605161850638387","guildId":"674357369106464918","animated":true,"oldName":"uhmmNope"},"umarupat":{"id":"703932768488521728","guildId":"683075970206531618","animated":true,"oldName":"umarupat"},"upfield":{"id":"867971910221307914","guildId":"688349038420033556","animated":false,"oldName":"Upfield"},"umimo":{"id":"939566133848207380","guildId":"688349038420033556","animated":false,"oldName":"Umimo"},"uwu_1":{"id":"831621873858773053","guildId":"698987568116531259","animated":false,"oldName":"uwu"},"upvote_0":{"id":"1186732031539937300","guildId":"698987568116531259","animated":false,"oldName":"upvote"},"umaruwtf_0":{"id":"880422202246307840","guildId":"750351983700869221","animated":false,"oldName":"umaruwtf"},"upvote_1":{"id":"874307969838366730","guildId":"791993321374613514","animated":false,"oldName":"upvote"},"uwattm8":{"id":"1094566132624658482","guildId":"791993321374613514","animated":false,"oldName":"uwattm8"},"uwottm8":{"id":"1095000665291509941","guildId":"791993321374613514","animated":false,"oldName":"uwottm8"},"uwottmate":{"id":"1095001294747484281","guildId":"791993321374613514","animated":false,"oldName":"uwottmate"},"uwattmate":{"id":"1095001390683787284","guildId":"791993321374613514","animated":false,"oldName":"uwattmate"},"uglykiss":{"id":"853783844800167967","guildId":"818692153681117235","animated":true,"oldName":"uglykiss"},"uhmwhat":{"id":"855509201965940777","guildId":"818692153681117235","animated":true,"oldName":"uhmwhat"},"urmommy":{"id":"1102884202875195452","guildId":"818692153681117235","animated":false,"oldName":"urmommy"},"ultradespair":{"id":"906810453169176606","guildId":"830700055451271188","animated":false,"oldName":"ultradespair"},"ult_raiden":{"id":"1069438247723356190","guildId":"901772018582691841","animated":true,"oldName":"ult_raiden"},"uwu_2":{"id":"1107586385516441720","guildId":"901772018582691841","animated":false,"oldName":"uwu"},"uhuh":{"id":"1164590599526170664","guildId":"901772018582691841","animated":false,"oldName":"uhuh"},"uhh":{"id":"1175586501313167440","guildId":"901772018582691841","animated":true,"oldName":"uhh"},"unlock":{"id":"1216350127397277786","guildId":"932529116400459786","animated":false,"oldName":"unlock"},"user":{"id":"1216350129662070815","guildId":"932529116400459786","animated":false,"oldName":"user"},"usershield":{"id":"1216350132451414016","guildId":"932529116400459786","animated":false,"oldName":"usershield"},"upvote_2":{"id":"981639725876133988","guildId":"949134467061153853","animated":false,"oldName":"upvote"},"ughlipbite":{"id":"985755225325449308","guildId":"949134467061153853","animated":false,"oldName":"ughLipbite"},"unamused":{"id":"1024444819822616706","guildId":"949134467061153853","animated":false,"oldName":"unamused"},"unshut":{"id":"1012680690619396136","guildId":"968096627002851379","animated":false,"oldName":"UNSHUT"},"ump9cum":{"id":"1084704223570182224","guildId":"968096627002851379","animated":false,"oldName":"UMP9cum"},"usagialice":{"id":"1099633230178689084","guildId":"968096627002851379","animated":true,"oldName":"UsagiAlice"},"uno_red_reverse_card":{"id":"1156600543960113294","guildId":"1075206519060172881","animated":false,"oldName":"Uno_Red_Reverse_Card"},"umm":{"id":"1165612312376393870","guildId":"1075206519060172881","animated":false,"oldName":"umm"},"uohh":{"id":"1165613302483787877","guildId":"1075206519060172881","animated":false,"oldName":"uohh"},"uwu_3":{"id":"1165723453194776647","guildId":"1075206519060172881","animated":false,"oldName":"uwu"},"uhhhh":{"id":"1207770555445420064","guildId":"1206436722053877820","animated":true,"oldName":"uhhhh"},"unshut_0":{"id":"1214543209787686922","guildId":"1206436722053877820","animated":false,"oldName":"unshut"},"ughpeepo":{"id":"1214543331787546664","guildId":"1206436722053877820","animated":false,"oldName":"ughpeepo"}}